design_3/led_fsm.v
////////////////////////////////////////////////////////////////
//  module LED FSM 
////////////////////////////////////////////////////////////////
module led_fsm(
	       input  sym_strt, symbol,
	       output led_drv, sym_done,
	       input  reset, clock
	       );
////////////////////////////////////////////////////////////////
//  parameter declarations
////////////////////////////////////////////////////////////////
   parameter START=3'b000;
   parameter DASH0=3'b001;
   parameter DASH1=3'b010;
   parameter DASH2=3'b011;
   parameter DOT0=3'b100;
   //declare each state name as a parameter

////////////////////////////////////////////////////////////////
//  State register for FSM
////////////////////////////////////////////////////////////////
   reg [2:0] 	     led_st;
 
   always @(posedge clock) begin
      led_st <= led_nx_st;
   end


////////////////////////////////////////////////////////////////
//  State and Output logic for statemachine
////////////////////////////////////////////////////////////////
   reg [2:0]  led_nx_st;
   reg 	      led_drv, sym_done; //outputs you need to generate
   
   always @(*) begin
      if (reset) begin
        led_drv = 1'b0;
        led_nx_st = START;
        sym_done = 1'b0;
      end
      else begin
	 case (led_st)
	   START: begin
         if(sym_strt == 1'b0) begin
           led_nx_st = START;
           led_drv = 1'b0;
           sym_done = 1'b0;
         end
         if(sym_strt == 1'b1) begin
           if(symbol == 1'b0) begin
             led_nx_st = DOT0;
             led_drv = 1'b1;
             sym_done = 1'b0;
           end
           if(symbol == 1'b1) begin
             led_nx_st = DASH0;
             led_drv = 1'b1;
             sym_done = 1'b0;
           end
         end
	   end // case: START
	   DOT0: begin
         led_nx_st = START;
         led_drv = 1'b0;
         sym_done = 1'b1;
       end // case: DOT0
       DASH0: begin
         led_nx_st = DASH1;
         led_drv = 1'b1;
         sym_done = 1'b0;
       end // case: DASH0
       DASH1: begin
         led_nx_st = DASH2;
         led_drv = 1'b1;
         sym_done = 1'b0;
       end // case: DASH1
       DASH2: begin
         led_nx_st = START;
         led_drv = 1'b0;
         sym_done = 1'b1;
       end // case: DASH2
	   default: begin  
	   end
	 endcase // case (led_st)
      end // else: !if(reset)
   end // always @ (*)
endmodule // led_fsm

design_3/code_reg.v
////////////////////////////////////////////////////////////////
//  module CODE REG
////////////////////////////////////////////////////////////////
/*
 There are 2 blocks to implement here. A counter and a shift register.
 Inputs (charcode_data and charlen_data) that represent the signal to be 
 encoded is loaded into these two elements to be processed.
 
 The shifter loads its values (charcode_data) with the signal char_load. 
 The shifter shifts to MSB whenever the signal shft_cnt is received.

 The counter loads the value charlen_data into its registers by the signal
   char_load.
 The counter counts down whenever the signal shft_cnt is received.
 One way to handle a "space" in the code is to load into the counter 4'b0111
   whenever you see a charlen_data = 4'b0000. That way you can use the 
   counter to count the number of blanks needed
 */
module code_reg(
		input [7:0]  charcode_data,
		input [3:0]  charlen_data,
		input 	     char_load, shft_cnt,
		output [3:0] cntr_data, 
		output 	     shft_data,
		input 	     reset, clock
		 );

////////////////////////////////////////////////////////////////
//  state register/FF for counter (cntr) and shifter (shftr)
////////////////////////////////////////////////////////////////
   reg [7:0] 	     shftr_o, shftr_i;
   reg [3:0] 	     cntr_o, cntr_i;

   always @(posedge clock) begin
      shftr_o <= shftr_i;
      cntr_o <= cntr_i;
   end

   wire		     shft_data;
   wire [3:0] 	     cntr_data;

   always @(*) begin
      if (reset) begin
	 shftr_i = 8'b00000000;
         cntr_i = 4'b0000;
      end
      else begin
	 if (char_load) begin //load overwrites any shifting or counting
       if(charlen_data == 4'b0000) begin
         cntr_i = 4'b0111;
       end
       else begin
       cntr_i = charlen_data;
       end
       shftr_i = charcode_data;
	 end
	 else begin //shift MSB 
	    if (shft_cnt) begin //shift to MSB and count down by 1
          shftr_i = shftr_i << shft_cnt;
          cntr_i = cntr_i - 1'b1;
	    end
	    else begin //no shift or count (keep the previous data)
	     
	    end
	 end // else: !if(char_load)
      end // else: !if(reset)
   end // always @ (reset or char_load or shft_cnt)

   assign cntr_data = cntr_o;
   assign shft_data = shftr_o[7];
   
endmodule // code_reg

design_3/dassign3.v
//`include "led_fsm.v"
//`include "code_reg.v"
////////////////////////////////////////////////////////////////
//  Main File for dassign3 
////////////////////////////////////////////////////////////////

////////////////////////////////////////////////////////////////
//  module dassign3 (also MORSE_ENCODER)
////////////////////////////////////////////////////////////////
module dassign3(
		input 	    char_vald,
		input [7:0] charcode_data,
		input [3:0] charlen_data,
		output 	    char_next, led_drv,
		input 	    reset, clock
		);

////////////////////////////////////////////////////////////////
//  Parameter Declarations
////////////////////////////////////////////////////////////////
  parameter START = 2'b00;
  parameter CHAR = 2'b01;
 
////////////////////////////////////////////////////////////////
//  Variable Declaration
////////////////////////////////////////////////////////////////

   // Outputs from modules       
   wire       shft_data, sym_done, led_drv; 
   wire [3:0] cntr_data; 

   // Signals that needs to be generated by this module
   reg 	      char_next, char_load, shft_cnt, sym_strt;

////////////////////////////////////////////////////////////////
//  Module Instantiation
////////////////////////////////////////////////////////////////

   code_reg codestore0(charcode_data, charlen_data, char_load, 
                       sym_done, cntr_data, shft_data, reset, clock);
   led_fsm ledfsm0(sym_strt, shft_data, led_drv, sym_done, 
                   reset, clock);
        
/* Some useful pseudo-code (you have to figure out if there are
   timing consideration or sequencing that you would want to do.
   From that, you can choose to build an FSM. You can choose to 
   build it as a separate module).
 
 symbol for led_fsm = shft_data from the shifter
 sym_strt is asserted when char_vald or after you've shifted 
    a new data symbol from the shifter

 space symbol is detected when charlen_data = 4'b0000      
 shft_cnt is asserted when sym_done is asserted (if using the 
    counter to deal with a space, you'd need to enable shft_cnt for 
    a "space" symbol)

 char_next for encoder = cntr counts down to 0
    (load counter with 4'b0111 when it is a space either in 
    code_reg or here)
 char_ vald input should trigger the char_load to grab the new 
    charcode_data and charlen_data
 */

////////////////////////////////////////////////////////////////
//  Your Code Here
////////////////////////////////////////////////////////////////
  reg[1:0] fsm_st;
  reg[1:0] fsm_nx_st;

  always @(posedge clock) begin
      fsm_st <= fsm_nx_st;
   end
  
  
  always @(*) begin
    
    if(reset) begin
      fsm_nx_st = START;
	end
    case(fsm_st)
      START: begin
        if(char_vald == 1'b1) begin
          	sym_strt = 1'b1;
          	char_next = 1'b0;
          	char_load = 1'b1;
          	shft_cnt = sym_done;
            fsm_nx_st = CHAR;
        end
		else
          	sym_strt = 1'b0;
      end
      CHAR: begin
		char_next = 1'b1;
        fsm_nx_st = START;
      end
    endcase
  end
      
endmodule // dassign3

design_3/dassign3_tb.v
//--------------------------------------------------------------------
//		Timescale
//--------------------------------------------------------------------
`timescale 1ns / 1ps
`define TCLK 40
`define THCYC 20
`define STRLEN 13
//--------------------------------------------------------------------
//		Design Assignment Testbench.
// ***YOU MUST MAKE SURE THAT YOUR CODE RUNS WITH THIS TEST BENCH***
//                   ***WITHOUT ANY MODIFICATION***
// Note: You may however use this testbench as a starting point to create 
// your own tests for debugging
//--------------------------------------------------------------------
/*
 * Utility module to generate a clock signal
 */
module clkgen(output clock);

   reg clock;

   always begin
      #`THCYC
	clock=~clock;
   end

   initial
     clock=1'b0;

endmodule // clkgen


module dassign3_tb();
//----------------------------------------------------------------
//		Parameters
//----------------------------------------------------------------
   
//----------------------------------------------------------------
//		Signal Declarations
//----------------------------------------------------------------
   wire       clock;
   reg 	      reset;

   wire       led_drv;
      
   wire [7:0] charcode_data;
   wire [3:0] charlen_data;

//----------------------------------------------------------------
//		Module Declaration
//----------------------------------------------------------------

   clkgen clkgen0(clock);
   dassign3 DUT(char_vald, charcode_data, charlen_data,
		char_next, led_drv,
		reset, clock
		);

////////////////////////////////////////////////////////////////
//  Variable Declaration
////////////////////////////////////////////////////////////////
   
   reg [`STRLEN*8-1:0] 	dut_str;

   reg 			char_vald;
   wire 		char_next;
 			
   reg [7:0] 		char;
   integer 		i, j, k;
 			
   reg [11:0] morse_mem[0:255];
   reg [11:0] morse_char;

   assign charcode_data[7:0] = morse_char[11:4];
   assign charlen_data[3:0] = morse_char[3:0];

   reg [3:0] 		kmax;

//
//----------------------------------------------------------------
//		Test Stimulus
//----------------------------------------------------------------
   initial begin
/*
 Dumping for display with epwave or gtkwave
 */
      $dumpfile("dassign3.vcd");
//      $dumpvars(0, DUT);
      $dumpvars(0);

      dut_str= "M16 TA FATIMA";
/*
 Reading the ascii-morse encoding table
 */
      $readmemb("./ascii_morse.txt", morse_mem);

      reset = 1'b1;
      #35
	char_vald = 1'b0;
      #`TCLK
	reset=1'b0;
      #`TCLK
      for(i=`STRLEN-1;i>=0;i=i-1) begin
      	 for(j=0;j<8;j=j+1) 
	    char[j] = dut_str[8*i+j];
	 morse_char = morse_mem[char];
	 char_vald = 1'b1;
	 #`TCLK
	 char_vald = 1'b0;
	 wait(char_next);
	 #(1.5*`TCLK)
	 $display("%s, %b, %b, %b",
		  char,morse_char,charlen_data,charcode_data);
      end // for (i=`STRLEN-1;i>=0;i=i-1)
      #(3*`TCLK)
      $finish;
   end // initial begin
   //
   //  Monitoring LED
   //
   integer led_cnt,cyc_cnt, sym_cnt;
   reg 	   led_sym, led_cnt_strt, sym_cnt_strt;
   reg [7:0] charcode_targ;
   reg [7:0] morse_seq;
   reg [3:0] charlen_targ;
 	   
   always @(posedge clock) begin
      if (char_vald) begin
	 sym_cnt = 0;
	 cyc_cnt = 0;
	 led_cnt = 0;
	 sym_cnt_strt = 1;
	 morse_seq = 8'b0000_0000;
	 charcode_targ = charcode_data;
	 charlen_targ = charlen_data;
      end
      if (sym_cnt_strt) begin //symbols counting
	 if (led_drv) begin //if LED then don't count blank cycles
	    led_cnt = led_cnt+1;
	    cyc_cnt = 0;
	 end
	 else begin
	    cyc_cnt = cyc_cnt+1; //when no LED: count blank cyc, and check count
	    if (led_cnt == 1) begin
	       $display("DOT detected");
	       morse_seq[7-sym_cnt] = 1'b0;
	       sym_cnt = sym_cnt+1;
	    end
	    else begin
	       if (led_cnt == 3) begin
		  $display("DASH detected");
		  morse_seq[7-sym_cnt] = 1'b1;
		  sym_cnt = sym_cnt+1;
	       end
	       else begin
		  $display("Blank detected (may be a fault)");
	       end
	    end // else: !if(led_drv)
	    led_cnt = 0; //blank the led count
	 end // else: !if(led_drv)
      end // if (sym_cnt_strt ==1)
   end // always @ (posedge clock)

   //
   // Hack to detect when to check if a character ends
   //
   always @(posedge char_next) begin 
      if (sym_cnt_strt) begin
//	 $display("sym: %b, symcnt:%b", morse_seq, sym_cnt);
	 if (cyc_cnt <= 3) begin
	    $display("Character Found:");
	    if (morse_seq == charcode_targ)
	      $display("\tMatch code: %b", morse_seq);
	    else 	   
	      $display("\tIncorrect Match to code: %b to: %b", morse_seq, charcode_targ);
	    if (sym_cnt == charlen_targ)
	      $display("\tMatch length: %b", sym_cnt);	   
	    else 	   
	      $display("\tIncorrect Match to length: %b to: %b", sym_cnt, charlen_targ);
	 end
         else begin
	   if ((cyc_cnt >=7) && (cyc_cnt<=12)) begin
	      $display("Space Found:");
	      if (charlen_targ == 4'b0000)
		$display("\tMatch space");
              else
	        $display("\tIncorrect Blanks");
	   end
	   else
	      $display("\tIncorrect Blanks");
	 end // else: !if(cyc_cnt <= 3)
	 sym_cnt_strt = 0;
      end // if (sym_cnt_strt == 1)
   end // always @ (posedge char_next)

endmodule // dassign3_tb

design_3/dassign3.vcd
$date
	Fri May 26 14:08:42 2017
$end
$version
	Icarus Verilog
$end
$timescale
	1ps
$end
$scope module dassign3_tb $end
$var wire 1 ! char_next $end
$var wire 8 " charcode_data [7:0] $end
$var wire 4 # charlen_data [3:0] $end
$var wire 1 $ clock $end
$var wire 1 % led_drv $end
$var reg 8 & char [7:0] $end
$var reg 1 ' char_vald $end
$var reg 8 ( charcode_targ [7:0] $end
$var reg 4 ) charlen_targ [3:0] $end
$var integer 32 * cyc_cnt [31:0] $end
$var reg 104 + dut_str [103:0] $end
$var integer 32 , i [31:0] $end
$var integer 32 - j [31:0] $end
$var integer 32 . led_cnt [31:0] $end
$var reg 12 / morse_char [11:0] $end
$var reg 8 0 morse_seq [7:0] $end
$var reg 1 1 reset $end
$var integer 32 2 sym_cnt [31:0] $end
$var reg 1 3 sym_cnt_strt $end
$scope module clkgen0 $end
$var reg 1 4 clock $end
$upscope $end
$scope module DUT $end
$var wire 1 5 char_vald $end
$var wire 8 6 charcode_data [7:0] $end
$var wire 4 7 charlen_data [3:0] $end
$var wire 1 $ clock $end
$var wire 4 8 cntr_data [3:0] $end
$var wire 1 % led_drv $end
$var wire 1 9 reset $end
$var wire 1 : shft_data $end
$var wire 1 ; sym_done $end
$var reg 1 < char_load $end
$var reg 1 = char_next $end
$var reg 2 > fsm_nx_st [1:0] $end
$var reg 2 ? fsm_st [1:0] $end
$var reg 1 @ shft_cnt $end
$var reg 1 A sym_strt $end
$scope module codestore0 $end
$var wire 1 B char_load $end
$var wire 8 C charcode_data [7:0] $end
$var wire 4 D charlen_data [3:0] $end
$var wire 1 $ clock $end
$var wire 4 E cntr_data [3:0] $end
$var wire 1 9 reset $end
$var wire 1 ; shft_cnt $end
$var wire 1 : shft_data $end
$var reg 4 F cntr_i [3:0] $end
$var reg 4 G cntr_o [3:0] $end
$var reg 8 H shftr_i [7:0] $end
$var reg 8 I shftr_o [7:0] $end
$upscope $end
$scope module ledfsm0 $end
$var wire 1 $ clock $end
$var wire 1 9 reset $end
$var wire 1 J sym_strt $end
$var wire 1 : symbol $end
$var reg 1 K led_drv $end
$var reg 3 L led_nx_st [2:0] $end
$var reg 3 M led_st [2:0] $end
$var reg 1 N sym_done $end
$upscope $end
$upscope $end
$upscope $end
$enddefinitions $end
#0
$dumpvars
0N
bx M
b0 L
0K
xJ
bx I
b0 H
bx G
b0 F
bx E
bx D
bx C
xB
xA
x@
bx ?
b0 >
x=
x<
0;
x:
19
bx 8
bx 7
bx 6
x5
04
x3
bx 2
11
bx 0
bx /
bx .
bx -
bx ,
b1001101001100010011011000100000010101000100000100100000010001100100000101010100010010010100110101000001 +
bx *
bx )
bx (
x'
bx &
0%
0$
bx #
bx "
x!
$end
#20000
0:
0A
0J
b0 G
b0 8
b0 E
b0 I
b0 M
b0 ?
14
1$
#35000
0'
05
#40000
04
0$
#60000
14
1$
#75000
01
09
#80000
04
0$
#100000
14
1$
#115000
1K
1%
b100 L
b11000000 H
b10 F
b1 >
0@
1<
1B
0=
0!
1A
1J
b11000000 "
b11000000 6
b11000000 C
b10 #
b10 7
b10 D
1'
15
b110000000010 /
b1001101 &
b1000 -
b1100 ,
#120000
04
0$
#140000
1@
1=
1!
b0 >
1N
1;
0K
0%
b0 L
1:
b1 ?
b100 M
b10 G
b10 8
b10 E
b11000000 I
b10 )
b11000000 (
b0 0
03
b1 .
b0 *
b0 2
14
1$
#155000
0'
05
#160000
04
0$
#180000
0N
0;
0A
0J
b0 M
b0 ?
14
1$
#200000
04
0$
#215000
1K
1%
b1 L
b1111000 H
b101 F
b1 >
0@
0=
0!
1A
1J
b1111000 "
b1111000 6
b1111000 C
b101 #
b101 7
b101 D
1'
15
b11110000101 /
b110001 &
b1000 -
b1011 ,
#220000
1@
1=
1!
b0 >
b10 L
0:
b1 ?
b1 M
b101 G
b101 8
b101 E
b1111000 I
b101 )
b1111000 (
03
b1 .
14
1$
#240000
04
0$
#255000
0'
05
#260000
b11 L
0A
0J
b10 M
b0 ?
14
1$
#280000
04
0$
#300000
1N
1;
0K
0%
b0 L
b11 M
14
1$
#315000
b10000000 H
b1 >
0@
0=
0!
1A
1J
b10000000 "
b10000000 6
b10000000 C
1'
15
b100000000101 /
b110110 &
b1000 -
b1010 ,
#320000
04
0$
#340000
1:
0N
0;
1K
1%
b1 L
1@
1=
1!
b0 >
b10000000 I
b0 M
b1 ?
b1 *
b10000000 (
03
b0 .
14
1$
#355000
0'
05
#360000
04
0$
#380000
0A
0J
b10 L
b0 ?
b1 M
14
1$
#400000
04
0$
#415000
b0 H
b111 F
b1 >
0@
0=
0!
1A
1J
b0 "
b0 6
b0 C
b0 #
b0 7
b0 D
1'
15
b0 /
b100000 &
b1000 -
b1001 ,
#420000
0:
b11 L
1@
1=
1!
b0 >
b111 G
b111 8
b111 E
b0 I
b10 M
b1 ?
b1 .
b0 )
b0 (
03
b0 *
14
1$
#440000
04
0$
#455000
0'
05
#460000
0A
0J
1N
1;
0K
0%
b0 L
b0 ?
b11 M
14
1$
#480000
04
0$
#500000
0N
0;
b0 M
14
1$
#515000
1K
1%
b100 L
b10000000 H
b1 F
b1 >
0@
0=
0!
1A
1J
b10000000 "
b10000000 6
b10000000 C
b1 #
b1 7
b1 D
1'
15
b100000000001 /
b1010100 &
b1000 -
b1000 ,
#520000
04
0$
#540000
1@
1=
1!
b0 >
1N
1;
0K
0%
b0 L
1:
b1 ?
b100 M
b1 G
b1 8
b1 E
b10000000 I
b1 )
b10000000 (
03
b1 .
14
1$
#555000
0'
05
#560000
04
0$
#580000
0N
0;
0A
0J
b0 M
b0 ?
14
1$
#600000
04
0$
#615000
1K
1%
b1 L
b1000000 H
b10 F
b1 >
0@
0=
0!
1A
1J
b1000000 "
b1000000 6
b1000000 C
b10 #
b10 7
b10 D
1'
15
b10000000010 /
b1000001 &
b1000 -
b111 ,
#620000
1@
1=
1!
b0 >
b10 L
0:
b1 ?
b1 M
b10 G
b10 8
b10 E
b1000000 I
b10 )
b1000000 (
03
b1 .
14
1$
#640000
04
0$
#655000
0'
05
#660000
b11 L
0A
0J
b10 M
b0 ?
14
1$
#680000
04
0$
#700000
1N
1;
0K
0%
b0 L
b11 M
14
1$
#715000
b0 H
b111 F
b1 >
0@
0=
0!
1A
1J
b0 "
b0 6
b0 C
b0 #
b0 7
b0 D
1'
15
b0 /
b100000 &
b1000 -
b110 ,
#720000
04
0$
#740000
0N
0;
1K
1%
b100 L
1@
1=
1!
b0 >
b111 G
b111 8
b111 E
b0 I
b0 M
b1 ?
b1 *
b0 )
b0 (
03
b0 .
14
1$
#755000
0'
05
#760000
04
0$
#780000
0A
0J
1N
1;
0K
0%
b0 L
b0 ?
b100 M
14
1$
#800000
04
0$
#815000
b100000 H
b100 F
b1 >
0@
0=
0!
1A
1J
b100000 "
b100000 6
b100000 C
b100 #
b100 7
b100 D
1'
15
b1000000100 /
b1000110 &
b1000 -
b101 ,
#820000
0N
0;
1K
1%
b100 L
1@
1=
1!
b0 >
b100 G
b100 8
b100 E
b100000 I
b0 M
b1 ?
b100 )
b100000 (
03
b1 *
14
1$
#840000
04
0$
#855000
0'
05
#860000
0A
0J
1N
1;
0K
0%
b0 L
b0 ?
b100 M
14
1$
#880000
04
0$
#900000
0N
0;
b0 M
14
1$
#915000
1K
1%
b100 L
b1000000 H
b10 F
b1 >
0@
0=
0!
1A
1J
b1000000 "
b1000000 6
b1000000 C
b10 #
b10 7
b10 D
1'
15
b10000000010 /
b1000001 &
b1000 -
b100 ,
#920000
04
0$
#940000
1@
1=
1!
b0 >
1N
1;
0K
0%
b0 L
b1 ?
b100 M
b10 G
b10 8
b10 E
b1000000 I
b1 .
b10 )
b1000000 (
03
b0 *
14
1$
#955000
0'
05
#960000
04
0$
#980000
0N
0;
0A
0J
b0 M
b0 ?
14
1$
#1000000
04
0$
#1015000
1K
1%
b100 L
b10000000 H
b1 F
b1 >
0@
0=
0!
1A
1J
b10000000 "
b10000000 6
b10000000 C
b1 #
b1 7
b1 D
1'
15
b100000000001 /
b1010100 &
b1000 -
b11 ,
#1020000
1@
1=
1!
b0 >
1N
1;
0K
0%
b0 L
1:
b1 ?
b100 M
b1 G
b1 8
b1 E
b10000000 I
b1 )
b10000000 (
03
b1 .
14
1$
#1040000
04
0$
#1055000
0'
05
#1060000
0N
0;
0A
0J
b0 M
b0 ?
14
1$
#1080000
04
0$
#1100000
14
1$
#1115000
1K
1%
b1 L
b0 H
b10 F
b1 >
0@
0=
0!
1A
1J
b0 "
b0 6
b0 C
b10 #
b10 7
b10 D
1'
15
b10 /
b1001001 &
b1000 -
b10 ,
#1120000
04
0$
#1140000
0:
b10 L
1@
1=
1!
b0 >
b10 G
b10 8
b10 E
b0 I
b1 M
b1 ?
b10 )
b0 (
03
b1 .
14
1$
#1155000
0'
05
#1160000
04
0$
#1180000
0A
0J
b11 L
b0 ?
b10 M
14
1$
#1200000
04
0$
#1215000
b11000000 H
b1 >
0@
0=
0!
1A
1J
b11000000 "
b11000000 6
b11000000 C
1'
15
b110000000010 /
b1001101 &
b1000 -
b1 ,
#1220000
1:
1N
1;
0K
0%
b0 L
1@
1=
1!
b0 >
b11000000 I
b11 M
b1 ?
b11000000 (
03
b1 .
14
1$
#1240000
04
0$
#1255000
0'
05
#1260000
0A
0J
0N
0;
0K
0%
b0 L
b0 ?
b0 M
14
1$
#1280000
04
0$
#1300000
14
1$
#1315000
1K
1%
b1 L
b1000000 H
b1 >
0@
0=
0!
1A
1J
b1000000 "
b1000000 6
b1000000 C
1'
15
b10000000010 /
b1000001 &
b1000 -
b0 ,
#1320000
04
0$
#1340000
1@
1=
1!
b0 >
b10 L
0:
b1 ?
b1 M
b1000000 I
b1000000 (
03
b1 .
14
1$
#1355000
0'
05
#1360000
04
0$
#1380000
b11 L
0A
0J
b10 M
b0 ?
14
1$
#1400000
04
0$
#1415000
b11111111111111111111111111111111 ,
#1420000
1N
1;
0K
0%
b0 L
b11 M
14
1$
#1440000
04
0$
#1460000
0N
0;
b0 M
14
1$
